{
  "batch_id": "whiskies_20260424T185200_98d3b1",
  "entity": "whiskies",
  "imported_at": "2026-04-24T18:52:00Z",
  "total": 1,
  "new": 0,
  "update_candidates": 0,
  "errors": 1,
  "incomplete": 0,
  "potential_duplicates": 0,
  "items": [
    {
      "raw": {
        "id": "nine-springs-triple-cask",
        "name": "The Nine Springs Triple Cask",
        "distillery_id": "number-nine",
        "whisky_type": "Single Malt",
        "abv": 45,
        "age": null,
        "nas": true,
        "tasting_notes_nose": "Sehr malzig mit reifen Früchten wie Pfirsich und getrockneter Pflaume, dazu Gewürze wie Nelke und Kardamom sowie Vanille und dunkle Schokolade.",
        "tasting_notes_palate": "Kraftvoller Antritt mit intensiven Noten von getrockneten Feigen, Kakao-Röstaromen und einer sanften Süße.",
        "tasting_notes_finish": "Voluminös mit einer leicht herben Tanninstruktur, die würzigen Noten klingen lange nach.",
        "seo_title": "Nine Springs Triple Cask | Thüringer Single Malt Whisky",
        "seo_description": "Der Nine Springs Triple Cask überzeugt durch komplexe Reifung in drei Fasstypen. Malzig, fruchtig und würzig."
      },
      "normalized": {
        "id": "nine-springs-triple-cask",
        "name": "The Nine Springs Triple Cask",
        "distillery_id": "number-nine",
        "whisky_type": "Single Malt",
        "abv": 45,
        "age": null,
        "nas": true,
        "tasting_notes_nose": "Sehr malzig mit reifen Früchten wie Pfirsich und getrockneter Pflaume, dazu Gewürze wie Nelke und Kardamom sowie Vanille und dunkle Schokolade.",
        "tasting_notes_palate": "Kraftvoller Antritt mit intensiven Noten von getrockneten Feigen, Kakao-Röstaromen und einer sanften Süße.",
        "tasting_notes_finish": "Voluminös mit einer leicht herben Tanninstruktur, die würzigen Noten klingen lange nach.",
        "seo_title": "Nine Springs Triple Cask | Thüringer Single Malt Whisky",
        "seo_description": "Der Nine Springs Triple Cask überzeugt durch komplexe Reifung in drei Fasstypen. Malzig, fruchtig und würzig.",
        "slug": "the-nine-springs-triple-cask",
        "created_at": "2026-04-24T18:52:00Z",
        "last_updated": "2026-04-24T18:52:00Z",
        "published": false
      },
      "status": "error",
      "errors": [
        "Pflichtfeld fehlt: country_id"
      ],
      "duplicate_candidates": [],
      "review_status": "pending",
      "reviewer_notes": "",
      "decision": null
    }
  ]
}