{
  "batch_id": "whiskies_20260426T151606_b20f06",
  "entity": "whiskies",
  "imported_at": "2026-04-26T15:16:06Z",
  "raw": [
    {
      "id": "origin-series-kentucky-straight-bourbon",
      "slug": "origin-series-kentucky-straight-bourbon",
      "name": "Origin Series Kentucky Straight Bourbon",
      "country_id": "usa",
      "region_id": "kentucky",
      "distillery_id": "bardstown-bourbon-co",
      "whisky_type": "bourbon",
      "style_tags": [],
      "age_statement": null,
      "nas": true,
      "abv": null,
      "cask_types": [],
      "smoke_profile": "none",
      "tasting_notes_nose": "",
      "tasting_notes_palate": "",
      "tasting_notes_finish": "",
      "short_description": "Origin Series Kentucky Straight Bourbon ist ein charaktervoller bourbon aus der Bardstown Bourbon Co..",
      "long_description": "Der Origin Series Kentucky Straight Bourbon repräsentiert den klassischen Stil der Bardstown Bourbon Co.. Sorgfältig hergestellt und gereift, bietet er ein authentisches Geschmackserlebnis aus Kentucky.",
      "editorial_notes": "",
      "travel_context": "",
      "image": null,
      "source_urls": [],
      "source_status": "verified",
      "review_status": "approved",
      "published": true,
      "related_articles": [],
      "seo_title": "Origin Series Kentucky Straight Bourbon | bourbon aus USA",
      "seo_description": "Entdecken Sie Origin Series Kentucky Straight Bourbon, einen erstklassigen bourbon von der Bardstown Bourbon Co. in Kentucky.",
      "created_at": "2026-04-24T21:16:37Z",
      "last_updated": "2026-04-24T21:16:37Z"
    }
  ]
}